{
  "id": 295,
  "name": "exploud",
  "order": 321,
  "gender_rate": 4,
  "capture_rate": 45,
  "base_happiness": 70,
  "is_baby": false,
  "hatch_counter": 20,
  "has_gender_differences": false,
  "forms_switchable": false,
  "growth_rate": "medium-slow",
  "pokedex_numbers": [
    {
      "entry_number": 142,
      "pokedex": {
        "name": "kalos-central"
      }
    },
    {
      "entry_number": 47,
      "pokedex": {
        "name": "hoenn"
      }
    },
    {
      "entry_number": 295,
      "pokedex": {
        "name": "national"
      }
    }
  ],
  "egg_groups": [
    "monster",
    "ground"
  ],
  "color": "blue",
  "shape": {
    "name": "upright"
  },
  "evolves_from_species": {
    "name": "loudred"
  },
  "evolution_chain": {},
  "habitat": {
    "name": "cave"
  },
  "generation": {
    "name": "generation-iii"
  },
  "names": {
    "ja": "バクオング",
    "en": "Exploud",
    "fr": "Brouhabam",
    "it": "Exploud",
    "de": "Krawumms",
    "es": "Exploud",
    "ko": "폭음룡"
  },
  "pal_park_encounters": [
    {
      "base_score": 80,
      "rate": 10,
      "area": {
        "name": "mountain"
      }
    }
  ],
  "form_descriptions": [],
  "genera": {
    "ja": "そうおん",
    "en": "Loud Noise",
    "fr": "Bruit Sourd",
    "it": "Fragore",
    "de": "Krach",
    "es": "Escandaloso",
    "ko": "소음"
  },
  "varieties": [
    {
      "is_default": true,
      "pokemon": {
        "name": "exploud"
      }
    }
  ],
  "first_evolution_id": 293,
  "types": [
    "normal"
  ],
  "base_stats": {
    "hp": 104,
    "attack": 91,
    "defense": 63,
    "special-attack": 91,
    "special-defense": 73,
    "speed": 68
  }
}