{
  "id": 33,
  "name": "nidorino",
  "order": 34,
  "gender_rate": 0,
  "capture_rate": 120,
  "base_happiness": 70,
  "is_baby": false,
  "hatch_counter": 20,
  "has_gender_differences": false,
  "forms_switchable": false,
  "growth_rate": "medium-slow",
  "pokedex_numbers": [
    {
      "entry_number": 108,
      "pokedex": {
        "name": "kalos-coastal"
      }
    },
    {
      "entry_number": 99,
      "pokedex": {
        "name": "updated-johto"
      }
    },
    {
      "entry_number": 99,
      "pokedex": {
        "name": "original-johto"
      }
    },
    {
      "entry_number": 33,
      "pokedex": {
        "name": "kanto"
      }
    },
    {
      "entry_number": 33,
      "pokedex": {
        "name": "national"
      }
    }
  ],
  "egg_groups": [
    "monster",
    "ground"
  ],
  "color": "purple",
  "shape": {
    "name": "quadruped"
  },
  "evolves_from_species": {
    "name": "nidoran-m"
  },
  "evolution_chain": {},
  "habitat": {
    "name": "grassland"
  },
  "generation": {
    "name": "generation-i"
  },
  "names": {
    "ja": "ニドリーノ",
    "en": "Nidorino",
    "fr": "Nidorino",
    "it": "Nidorino",
    "de": "Nidorino",
    "es": "Nidorino",
    "ko": "니드리노"
  },
  "pal_park_encounters": [
    {
      "base_score": 50,
      "rate": 30,
      "area": {
        "name": "field"
      }
    }
  ],
  "form_descriptions": [],
  "genera": {
    "ja": "どくばり",
    "en": "Poison Pin",
    "fr": "Vénépic",
    "it": "Velenago",
    "de": "Giftdorn",
    "es": "Pin Veneno",
    "ko": "독침"
  },
  "varieties": [
    {
      "is_default": true,
      "pokemon": {
        "name": "nidorino"
      }
    }
  ],
  "first_evolution_id": 32,
  "types": [
    "poison"
  ],
  "base_stats": {
    "hp": 61,
    "attack": 72,
    "defense": 57,
    "special-attack": 55,
    "special-defense": 55,
    "speed": 65
  }
}