{
  "id": 40,
  "name": "wigglytuff",
  "order": 43,
  "gender_rate": 6,
  "capture_rate": 50,
  "base_happiness": 70,
  "is_baby": false,
  "hatch_counter": 10,
  "has_gender_differences": false,
  "forms_switchable": false,
  "growth_rate": "fast",
  "pokedex_numbers": [
    {
      "entry_number": 121,
      "pokedex": {
        "name": "kalos-mountain"
      }
    },
    {
      "entry_number": 22,
      "pokedex": {
        "name": "conquest-gallery"
      }
    },
    {
      "entry_number": 283,
      "pokedex": {
        "name": "updated-unova"
      }
    },
    {
      "entry_number": 45,
      "pokedex": {
        "name": "updated-johto"
      }
    },
    {
      "entry_number": 139,
      "pokedex": {
        "name": "hoenn"
      }
    },
    {
      "entry_number": 45,
      "pokedex": {
        "name": "original-johto"
      }
    },
    {
      "entry_number": 40,
      "pokedex": {
        "name": "kanto"
      }
    },
    {
      "entry_number": 40,
      "pokedex": {
        "name": "national"
      }
    }
  ],
  "egg_groups": [
    "fairy"
  ],
  "color": "pink",
  "shape": {
    "name": "humanoid"
  },
  "evolves_from_species": {
    "name": "jigglypuff"
  },
  "evolution_chain": {},
  "habitat": {
    "name": "grassland"
  },
  "generation": {
    "name": "generation-i"
  },
  "names": {
    "ja": "プクリン",
    "en": "Wigglytuff",
    "fr": "Grodoudou",
    "it": "Wigglytuff",
    "de": "Knuddeluff",
    "es": "Wigglytuff",
    "ko": "푸크린"
  },
  "pal_park_encounters": [
    {
      "base_score": 90,
      "rate": 3,
      "area": {
        "name": "field"
      }
    }
  ],
  "form_descriptions": [],
  "genera": {
    "ja": "ふうせん",
    "en": "Balloon",
    "fr": "Bouboule",
    "it": "Pallone",
    "de": "Ballon",
    "es": "Globo",
    "ko": "풍선"
  },
  "varieties": [
    {
      "is_default": true,
      "pokemon": {
        "name": "wigglytuff"
      }
    }
  ],
  "first_evolution_id": 174,
  "types": [
    "normal",
    "fairy"
  ],
  "base_stats": {
    "hp": 140,
    "attack": 70,
    "defense": 45,
    "special-attack": 85,
    "special-defense": 50,
    "speed": 45
  }
}