{
  "id": 435,
  "name": "skuntank",
  "order": 459,
  "gender_rate": 4,
  "capture_rate": 60,
  "base_happiness": 70,
  "is_baby": false,
  "hatch_counter": 20,
  "has_gender_differences": false,
  "forms_switchable": false,
  "growth_rate": "medium",
  "pokedex_numbers": [
    {
      "entry_number": 103,
      "pokedex": {
        "name": "kalos-coastal"
      }
    },
    {
      "entry_number": 85,
      "pokedex": {
        "name": "extended-sinnoh"
      }
    },
    {
      "entry_number": 85,
      "pokedex": {
        "name": "original-sinnoh"
      }
    },
    {
      "entry_number": 435,
      "pokedex": {
        "name": "national"
      }
    }
  ],
  "egg_groups": [
    "ground"
  ],
  "color": "purple",
  "shape": {
    "name": "quadruped"
  },
  "evolves_from_species": {
    "name": "stunky"
  },
  "evolution_chain": {},
  "habitat": null,
  "generation": {
    "name": "generation-iv"
  },
  "names": {
    "ja": "スカタンク",
    "en": "Skuntank",
    "fr": "Moufflair",
    "it": "Skuntank",
    "de": "Skuntank",
    "es": "Skuntank",
    "ko": "스컹탱크"
  },
  "pal_park_encounters": [
    {
      "base_score": 50,
      "rate": 30,
      "area": {
        "name": "mountain"
      }
    }
  ],
  "form_descriptions": [],
  "genera": {
    "ja": "スカンク",
    "en": "Skunk",
    "fr": "Moufette",
    "it": "Moffetta",
    "de": "Stinktier",
    "es": "Mofeta",
    "ko": "스컹크"
  },
  "varieties": [
    {
      "is_default": true,
      "pokemon": {
        "name": "skuntank"
      }
    }
  ],
  "first_evolution_id": 434,
  "types": [
    "poison",
    "dark"
  ],
  "base_stats": {
    "hp": 103,
    "attack": 93,
    "defense": 67,
    "special-attack": 71,
    "special-defense": 61,
    "speed": 84
  }
}