{
  "id": 529,
  "name": "drilbur",
  "order": 530,
  "gender_rate": 4,
  "capture_rate": 120,
  "base_happiness": 70,
  "is_baby": false,
  "hatch_counter": 20,
  "has_gender_differences": false,
  "forms_switchable": false,
  "growth_rate": "medium",
  "pokedex_numbers": [
    {
      "entry_number": 152,
      "pokedex": {
        "name": "conquest-gallery"
      }
    },
    {
      "entry_number": 76,
      "pokedex": {
        "name": "updated-unova"
      }
    },
    {
      "entry_number": 35,
      "pokedex": {
        "name": "original-unova"
      }
    },
    {
      "entry_number": 529,
      "pokedex": {
        "name": "national"
      }
    }
  ],
  "egg_groups": [
    "ground"
  ],
  "color": "gray",
  "shape": {
    "name": "upright"
  },
  "evolves_from_species": null,
  "evolution_chain": {},
  "habitat": null,
  "generation": {
    "name": "generation-v"
  },
  "names": {
    "ja": "モグリュー",
    "en": "Drilbur",
    "fr": "Rototaupe",
    "it": "Drilbur",
    "de": "Rotomurf",
    "es": "Drilbur",
    "ko": "두더류"
  },
  "pal_park_encounters": [],
  "form_descriptions": [],
  "genera": {
    "ja": "もぐら",
    "en": "Mole",
    "fr": "Taupe",
    "it": "Talpa",
    "de": "Maulwurf",
    "es": "Topo",
    "ko": "두더지"
  },
  "varieties": [
    {
      "is_default": true,
      "pokemon": {
        "name": "drilbur"
      }
    }
  ],
  "first_evolution_id": 529,
  "types": [
    "ground"
  ],
  "base_stats": {
    "hp": 60,
    "attack": 85,
    "defense": 40,
    "special-attack": 30,
    "special-defense": 45,
    "speed": 68
  }
}