{
  "id": 623,
  "name": "golurk",
  "order": 624,
  "gender_rate": -1,
  "capture_rate": 90,
  "base_happiness": 70,
  "is_baby": false,
  "hatch_counter": 25,
  "has_gender_differences": false,
  "forms_switchable": false,
  "growth_rate": "medium",
  "pokedex_numbers": [
    {
      "entry_number": 92,
      "pokedex": {
        "name": "kalos-coastal"
      }
    },
    {
      "entry_number": 272,
      "pokedex": {
        "name": "updated-unova"
      }
    },
    {
      "entry_number": 129,
      "pokedex": {
        "name": "original-unova"
      }
    },
    {
      "entry_number": 623,
      "pokedex": {
        "name": "national"
      }
    }
  ],
  "egg_groups": [
    "mineral"
  ],
  "color": "green",
  "shape": {
    "name": "humanoid"
  },
  "evolves_from_species": {
    "name": "golett"
  },
  "evolution_chain": {},
  "habitat": null,
  "generation": {
    "name": "generation-v"
  },
  "names": {
    "ja": "ゴルーグ",
    "en": "Golurk",
    "fr": "Golemastoc",
    "it": "Golurk",
    "de": "Golgantes",
    "es": "Golurk",
    "ko": "골루그"
  },
  "pal_park_encounters": [],
  "form_descriptions": [],
  "genera": {
    "ja": "ゴーレム",
    "en": "Automaton",
    "fr": "Golem Ancien",
    "it": "Statuanimata",
    "de": "Urgolem",
    "es": "Autómata",
    "ko": "골렘"
  },
  "varieties": [
    {
      "is_default": true,
      "pokemon": {
        "name": "golurk"
      }
    }
  ],
  "first_evolution_id": 622,
  "types": [
    "ground",
    "ghost"
  ],
  "base_stats": {
    "hp": 89,
    "attack": 124,
    "defense": 80,
    "special-attack": 55,
    "special-defense": 80,
    "speed": 55
  }
}