{
  "id": 684,
  "name": "swirlix",
  "order": 685,
  "gender_rate": 4,
  "capture_rate": 200,
  "base_happiness": 70,
  "is_baby": false,
  "hatch_counter": 20,
  "has_gender_differences": false,
  "forms_switchable": false,
  "growth_rate": "medium",
  "pokedex_numbers": [
    {
      "entry_number": 131,
      "pokedex": {
        "name": "kalos-central"
      }
    },
    {
      "entry_number": 684,
      "pokedex": {
        "name": "national"
      }
    }
  ],
  "egg_groups": [
    "fairy"
  ],
  "color": "white",
  "shape": {
    "name": "legs"
  },
  "evolves_from_species": null,
  "evolution_chain": {},
  "habitat": null,
  "generation": {
    "name": "generation-vi"
  },
  "names": {
    "ja": "ペロッパフ",
    "en": "Swirlix",
    "fr": "Sucroquin",
    "it": "Swirlix",
    "de": "Flauschling",
    "es": "Swirlix",
    "ko": "나룸퍼프"
  },
  "pal_park_encounters": [],
  "form_descriptions": [],
  "genera": {
    "ja": "わたあめ",
    "en": "Cotton Candy",
    "fr": "Confiserie",
    "it": "Zuccherino",
    "de": "Zuckerwatte",
    "es": "Chuchería",
    "ko": "솜사탕"
  },
  "varieties": [
    {
      "is_default": true,
      "pokemon": {
        "name": "swirlix"
      }
    }
  ],
  "first_evolution_id": 684,
  "types": [
    "fairy"
  ],
  "base_stats": {
    "hp": 62,
    "attack": 48,
    "defense": 66,
    "special-attack": 59,
    "special-defense": 57,
    "speed": 49
  }
}