{
  "id": 701,
  "name": "hawlucha",
  "order": 701,
  "gender_rate": 4,
  "capture_rate": 100,
  "base_happiness": 70,
  "is_baby": false,
  "hatch_counter": 20,
  "has_gender_differences": false,
  "forms_switchable": false,
  "growth_rate": "medium",
  "pokedex_numbers": [
    {
      "entry_number": 89,
      "pokedex": {
        "name": "kalos-coastal"
      }
    },
    {
      "entry_number": 701,
      "pokedex": {
        "name": "national"
      }
    }
  ],
  "egg_groups": [
    "humanshape"
  ],
  "color": "green",
  "shape": {
    "name": "humanoid"
  },
  "evolves_from_species": null,
  "evolution_chain": {},
  "habitat": null,
  "generation": {
    "name": "generation-vi"
  },
  "names": {
    "ja": "ルチャブル",
    "en": "Hawlucha",
    "fr": "Brutalibré",
    "it": "Hawlucha",
    "de": "Resladero",
    "es": "Hawlucha",
    "ko": "루차불"
  },
  "pal_park_encounters": [],
  "form_descriptions": [],
  "genera": {
    "ja": "レスリング",
    "en": "Wrestling",
    "fr": "Catcheur",
    "it": "Lottalibera",
    "de": "Wrestling",
    "es": "Lucha Libre",
    "ko": "레슬링"
  },
  "varieties": [
    {
      "is_default": true,
      "pokemon": {
        "name": "hawlucha"
      }
    }
  ],
  "first_evolution_id": 701,
  "types": [
    "fighting",
    "flying"
  ],
  "base_stats": {
    "hp": 78,
    "attack": 92,
    "defense": 75,
    "special-attack": 74,
    "special-defense": 63,
    "speed": 118
  }
}