{"id":25,"name":"pikachu","order":26,"gender_rate":4,"capture_rate":190,"base_happiness":70,"is_baby":false,"hatch_counter":10,"has_gender_differences":true,"forms_switchable":false,"growth_rate":{"name":"medium"},"pokedex_numbers":[{"entry_number":36,"pokedex":{"name":"kalos-central"}},{"entry_number":16,"pokedex":{"name":"conquest-gallery"}},{"entry_number":22,"pokedex":{"name":"updated-johto"}},{"entry_number":104,"pokedex":{"name":"extended-sinnoh"}},{"entry_number":104,"pokedex":{"name":"original-sinnoh"}},{"entry_number":156,"pokedex":{"name":"hoenn"}},{"entry_number":22,"pokedex":{"name":"original-johto"}},{"entry_number":25,"pokedex":{"name":"kanto"}},{"entry_number":25,"pokedex":{"name":"national"}}],"egg_groups":[{"name":"fairy"},{"name":"ground"}],"color":{"name":"yellow"},"shape":{"name":"quadruped"},"evolves_from_species":{"name":"pichu"},"evolution_chain":{},"habitat":{"name":"forest"},"generation":{"name":"generation-i"},"names":[{"name":"ピカチュウ","language":"ja"},{"name":"Pikachu","language":"roomaji"},{"name":"피카츄","language":"ko"},{"name":"皮卡丘","language":"zh"},{"name":"Pikachu","language":"fr"},{"name":"Pikachu","language":"de"},{"name":"Pikachu","language":"es"},{"name":"Pikachu","language":"it"},{"name":"Pikachu","language":"en"}],"pal_park_encounters":[{"base_score":80,"rate":10,"area":{"name":"forest"}}],"form_descriptions":[],"genera":[{"genus":"ねずみ","language":"ja"},{"genus":"쥐","language":"ko"},{"genus":"Souris","language":"fr"},{"genus":"Maus","language":"de"},{"genus":"Ratón","language":"es"},{"genus":"Topo","language":"it"},{"genus":"Mouse","language":"en"}],"varieties":[{"is_default":true,"pokemon":{"name":"pikachu"}}],"first_evolution_id":172}