{"id":624,"name":"pawniard","order":625,"gender_rate":4,"capture_rate":120,"base_happiness":35,"is_baby":false,"hatch_counter":20,"has_gender_differences":false,"forms_switchable":false,"growth_rate":{"name":"medium"},"pokedex_numbers":[{"entry_number":48,"pokedex":{"name":"kalos-mountain"}},{"entry_number":158,"pokedex":{"name":"conquest-gallery"}},{"entry_number":223,"pokedex":{"name":"updated-unova"}},{"entry_number":130,"pokedex":{"name":"original-unova"}},{"entry_number":624,"pokedex":{"name":"national"}}],"egg_groups":[{"name":"humanshape"}],"color":{"name":"red"},"shape":{"name":"humanoid"},"evolves_from_species":null,"evolution_chain":{},"habitat":null,"generation":{"name":"generation-v"},"names":[{"name":"コマタナ","language":"ja"},{"name":"자망칼","language":"ko"},{"name":"Scalpion","language":"fr"},{"name":"Gladiantri","language":"de"},{"name":"Pawniard","language":"es"},{"name":"Pawniard","language":"it"},{"name":"Pawniard","language":"en"}],"pal_park_encounters":[],"form_descriptions":[],"genera":[{"genus":"はもの","language":"ja"},{"genus":"날붙이","language":"ko"},{"genus":"Coupant","language":"fr"},{"genus":"Stahlklinge","language":"de"},{"genus":"Tajo","language":"es"},{"genus":"Lamaffilata","language":"it"},{"genus":"Sharp Blade","language":"en"}],"varieties":[{"is_default":true,"pokemon":{"name":"pawniard"}}]}