{
  "id": 321,
  "name": "tickle",
  "accuracy": 100,
  "pp": 20,
  "priority": 0,
  "power": null,
  "damage_class": "status",
  "meta": {
    "ailment": "none",
    "category": "net-good-stats",
    "min_hits": null,
    "max_hits": null,
    "min_turns": null,
    "max_turns": null,
    "drain": 0,
    "healing": 0,
    "crit_rate": 0,
    "ailment_chance": 0,
    "flinch_chance": 0,
    "stat_chance": 0
  },
  "names": {
    "ja": "くすぐる",
    "kana": "くすぐる",
    "en": "Tickle",
    "fr": "Chatouille",
    "it": "Solletico",
    "de": "Spaßkanone",
    "es": "Cosquillas",
    "ko": "간지르기",
    "zh-CN": "挠痒",
    "zh-TW": "搔癢"
  },
  "flavor_text_entries": {
    "ja": "体を　くすぐり　笑わせる　ことで 相手の　攻撃と　防御を　さげる。",
    "kana": "からだを　くすぐり　わらわせる　ことで あいての　こうげきと　ぼうぎょを さげる。",
    "en": "The user tickles the target into laughing, reducing its Attack and Defense stats.",
    "fr": "Le lanceur chatouille l’ennemi, ce qui baisse son Attaque et sa Défense.",
    "it": "Chi la usa solletica il bersaglio e lo fa ridere, riducendo il suo Attacco e la sua Difesa.",
    "de": "Bringt das Ziel zum Lachen und senkt dadurch dessen Angriff und Verteidigung.",
    "es": "Hace reír al objetivo para bajar su Ataque y Defensa.",
    "ko": "몸을 간질여 웃게 만들어서 상대의 공격과 방어를 떨어뜨린다.",
    "zh-CN": "给对手挠痒，使其发笑， 从而降低对手的攻击和防御。",
    "zh-TW": "搔癢對手的身體，讓對手發笑， 降低對手的攻擊和防禦。"
  },
  "stat_changes": [
    {
      "change": -1,
      "stat": "attack"
    },
    {
      "change": -1,
      "stat": "defense"
    }
  ],
  "target": "selected-pokemon",
  "type": "normal"
}
