{
  "id": 416,
  "name": "giga-impact",
  "accuracy": 90,
  "pp": 5,
  "priority": 0,
  "power": 150,
  "damage_class": "physical",
  "meta": {
    "ailment": "none",
    "category": "damage",
    "min_hits": null,
    "max_hits": null,
    "min_turns": null,
    "max_turns": null,
    "drain": 0,
    "healing": 0,
    "crit_rate": 0,
    "ailment_chance": 0,
    "flinch_chance": 0,
    "stat_chance": 0
  },
  "names": {
    "ja": "ギガインパクト",
    "kana": "ギガインパクト",
    "en": "Giga Impact",
    "fr": "Giga Impact",
    "it": "Gigaimpatto",
    "de": "Gigastoß",
    "es": "Giga Impacto",
    "ko": "기가임팩트",
    "zh-CN": "终极冲击",
    "zh-TW": "終極衝擊"
  },
  "flavor_text_entries": {
    "ja": "持てる　力を　すべて　使って 相手に　突撃する。 次の　ターンは　動けなくなる。",
    "kana": "もてる　ちからを　すべて　つかって あいてに　とつげきする。 つぎの　ターンは　うごけなく　なる。",
    "en": "The user charges at the target using every bit of its power. The user can’t move on the next turn.",
    "fr": "Le lanceur charge l’ennemi de toute sa puissance et doit ensuite se reposer au tour suivant.",
    "it": "Chi la usa carica il bersaglio usando tutta la sua forza, ma al turno successivo deve riposarsi.",
    "de": "Anwender rennt mit seiner ganzen Kraft gegen das Ziel an und muss dann eine Runde ruhen.",
    "es": "Carga contra el objetivo usando toda la fuerza que tiene. El Pokémon descansa el turno siguiente.",
    "ko": "가진 힘을 모두 사용해서 상대에게 돌격한다. 다음 턴은 움직일 수 없다.",
    "zh-CN": "使出自己浑身力量突击对手。 下一回合自己将无法动弹。",
    "zh-TW": "使出全身上下所有力量突擊對手。 下一回合自己將無法動彈。"
  },
  "stat_changes": [],
  "target": "selected-pokemon",
  "type": "normal"
}
