{
  "id": 432,
  "name": "defog",
  "accuracy": null,
  "pp": 15,
  "priority": 0,
  "power": null,
  "damage_class": "status",
  "meta": {
    "ailment": "none",
    "category": "unique",
    "min_hits": null,
    "max_hits": null,
    "min_turns": null,
    "max_turns": null,
    "drain": 0,
    "healing": 0,
    "crit_rate": 0,
    "ailment_chance": 0,
    "flinch_chance": 0,
    "stat_chance": 0
  },
  "names": {
    "ja": "きりばらい",
    "kana": "きりばらい",
    "en": "Defog",
    "fr": "Anti-Brume",
    "it": "Scacciabruma",
    "de": "Auflockern",
    "es": "Despejar",
    "ko": "안개제거",
    "zh-CN": "清除浓雾",
    "zh-TW": "清除濃霧"
  },
  "flavor_text_entries": {
    "ja": "強い風で　相手の　リフレクターや ひかりのかべ　などを　はらいのける。 回避率も　さげる。",
    "kana": "つよいかぜで　あいての　リフレクターや ひかりのかべ　などを　はらいのける。 かいひりつも　さげる。",
    "en": "A strong wind blows away the target’s barriers such as Reflect or Light Screen. This also lowers the target’s evasiveness.",
    "fr": "Un grand coup de vent qui disperse la Protection ou le Mur Lumière de l’ennemi. Diminue aussi son Esquive.",
    "it": "Chi la usa spazza via barriere come Riflesso e Schermoluce con un forte vento e riduce la capacità d’elusione del bersaglio.",
    "de": "Starker Wind hebt Attacken wie Reflektor und Lichtschild des Zieles auf. Senkt außerdem den Fluchtwert.",
    "es": "Potente viento que barre el Reflejo o Pantalla de Luz del objetivo y puede reducir su Evasión.",
    "ko": "강한 바람으로 상대의 리플렉터나 빛의장막 등을 제거한다. 회피율도 떨어뜨린다.",
    "zh-CN": "用强风吹开对手的 反射壁或光墙等。 也会降低对手的闪避率。",
    "zh-TW": "用強風吹開對手的 反射壁或光牆等。 也會降低對手的閃避率。"
  },
  "stat_changes": [],
  "target": "selected-pokemon",
  "type": "flying"
}
