{
  "id": 477,
  "name": "squirt-bottle",
  "names": {
    "ja": "ゼニガメじょうろ",
    "kana": "ゼニガメじょうろ",
    "en": "Squirt Bottle",
    "fr": "Carapuce à O",
    "it": "Annaffiatoio",
    "de": "Schiggykanne",
    "es": "Regadera",
    "ko": "꼬부기물뿌리개",
    "zh-CN": "杰尼龟喷壶",
    "zh-TW": "傑尼龜噴壺"
  },
  "flavor_text_entries": {
    "ja": "みずを　かける　道具。 きのみプランターの　きのみを すくすく　育てる。",
    "kana": "みずを　かける　どうぐ。 きのみプランターの　きのみを すくすく　そだてる。",
    "en": "A bottle used for watering plants in the Berry Pots.",
    "fr": "Un arrosoir qui permet de faire croître rapidement les Baies plantées dans le Plante-Baies.",
    "it": "Strumento che serve a innaffiare. Permette un’ottima crescita delle bacche seminate nel Piantabacche.",
    "de": "Eine Gießkanne, durch deren Wasser Beeren im Pflanzset umso rascher wachsen.",
    "es": "Objeto que contiene agua y se usa para regar las bayas del Plantabayas.",
    "ko": "물을 주는 도구. 나무열매플랜터의 나무열매를 쑥쑥 키운다.",
    "zh-CN": "浇水的道具。 能让树果种植盆里的 树果快快长大。",
    "zh-TW": "澆水的器具。 能讓樹果種植盆裡的 樹果快快長大。"
  }
}
