{
  "id": 776,
  "name": "normalium-z",
  "names": {
    "ja": "ノーマルＺ",
    "en": "Normalium Z",
    "fr": "Normazélite",
    "it": "Normium Z",
    "de": "Normium Z",
    "es": "Normastal Z",
    "ko": "노말Z",
    "zh-CN": "一般Ｚ",
    "zh-TW": "一般Ｚ"
  },
  "flavor_text_entries": {
    "ja": "Ｚパワーの　結晶。 ノーマルタイプの　技を Ｚワザに　グレードアップする。",
    "kana": "Ｚパワーの　けっしょう。 ノーマルタイプの　わざを Ｚワザに　グレードアップする。",
    "en": "This is a crystallized form of Z-Power. It upgrades Normal-type moves to Z-Moves.",
    "fr": "Une cristallisation de la Force Z, permettant de transformer les capacités de type Normal en capacité Z.",
    "it": "Cristallo in cui è immagazzinato il Potere Z. Consente di trasformare le mosse di tipo Normale in mosse Z.",
    "de": "Ein Kristall, dem Z-Kraft innewohnt. Er stuft Normal-Attacken zu Z-Attacken auf.",
    "es": "Cristal que confiere el Poder Z a los movimientos de tipo Normal.",
    "ko": "Z파워의 결정. 노말타입 기술을 Z기술로 업그레이드한다.",
    "zh-CN": "Ｚ力量的结晶。 会将一般属性的招式 升级成Ｚ招式。",
    "zh-TW": "Ｚ力量的結晶。 會把一般屬性的招式 升級為Ｚ招式。"
  }
}
