{
  "id": 792,
  "name": "steelium-z",
  "names": {
    "ja": "ハガネＺ",
    "en": "Steelium Z",
    "fr": "Métallozélite",
    "it": "Metallium Z",
    "de": "Metallium Z",
    "es": "Metalostal Z",
    "ko": "강철Z",
    "zh-CN": "钢Ｚ",
    "zh-TW": "鋼Ｚ"
  },
  "flavor_text_entries": {
    "ja": "Ｚパワーの　結晶。 はがねタイプの　技を Ｚワザに　グレードアップする。",
    "kana": "Ｚパワーの　けっしょう。 はがねタイプの　わざを Ｚワザに　グレードアップする。",
    "en": "This is a crystallized form of Z-Power. It upgrades Steel-type moves to Z-Moves.",
    "fr": "Une cristallisation de la Force Z, permettant de transformer les capacités de type Acier en capacité Z.",
    "it": "Cristallo in cui è immagazzinato il Potere Z. Consente di trasformare le mosse di tipo Acciaio in mosse Z.",
    "de": "Ein Kristall, dem Z-Kraft innewohnt. Er stuft Stahl-Attacken zu Z-Attacken auf.",
    "es": "Cristal que confiere el Poder Z a los movimientos de tipo Acero.",
    "ko": "Z파워의 결정. 강철타입 기술을 Z기술로 업그레이드한다.",
    "zh-CN": "Ｚ力量的结晶。 会将钢属性的招式 升级成Ｚ招式。",
    "zh-TW": "Ｚ力量的結晶。 會把鋼屬性的招式 升級為Ｚ招式。"
  }
}
