{
  "id": 800,
  "name": "primarium-z",
  "names": {
    "ja": "アシレーヌＺ",
    "en": "Primarium Z",
    "fr": "Oratozélite",
    "it": "Primarinium Z",
    "de": "Primarenium Z",
    "es": "Primastal Z",
    "ko": "누리레느Z",
    "zh-CN": "西狮海壬Ｚ",
    "zh-TW": "西獅海壬Ｚ"
  },
  "flavor_text_entries": {
    "ja": "Ｚパワーの　結晶。 アシレーヌの　うたかたのアリアを Ｚワザに　グレードアップする。",
    "kana": "Ｚパワーの　けっしょう。 アシレーヌの　うたかたのアリアを Ｚワザに　グレードアップする。",
    "en": "This is a crystallized form of Z-Power. It upgrades Primarina’s Sparkling Aria to a Z-Move.",
    "fr": "Une cristallisation de la Force Z, permettant de transformer l’Aria de l’Écume d’un Oratoria en capacité Z.",
    "it": "Cristallo in cui è immagazzinato il Potere Z. Consente di trasformare la mossa Canto Effimero di Primarina in una mossa Z.",
    "de": "Ein Kristall, dem Z-Kraft innewohnt. Er stuft Primarenes Attacke Schaumserenade zu einer Z-Attacke auf.",
    "es": "Cristal que confiere el Poder Z al movimiento Aria Burbuja de Primarina.",
    "ko": "Z파워의 결정. 누리레느의 물거품아리아를 Z기술로 업그레이드한다.",
    "zh-CN": "Ｚ力量的结晶。 会将西狮海壬的泡影的咏叹调 升级成Ｚ招式。",
    "zh-TW": "Ｚ力量的結晶。 會把西獅海壬的泡影的詠歎調 升級為Ｚ招式。"
  }
}
