{
  "id": 37,
  "name": "huge-power",
  "names": {
    "ja": "ちからもち",
    "kana": "ちからもち",
    "en": "Huge Power",
    "fr": "Coloforce",
    "it": "Macroforza",
    "de": "Kraftkoloss",
    "es": "Potencia",
    "ko": "천하장사",
    "zh-CN": "大力士",
    "zh-TW": "大力士"
  },
  "flavor_text_entries": {
    "ja": "物理攻撃の 威力が　２倍になる。",
    "kana": "ぶつり　こうげきの いりょくが　２ばいに　なる。",
    "en": "Doubles the Pokémon’s Attack stat.",
    "fr": "Double l’Attaque du Pokémon.",
    "it": "L’Attacco del Pokémon raddoppia.",
    "de": "Verdoppelt die Stärke von physischen Attacken.",
    "es": "Duplica la potencia de los ataques físicos.",
    "ko": "물리공격의 위력이 2배가 된다.",
    "zh-CN": "物理攻击的威力会变为２倍。",
    "zh-TW": "物理攻擊的威力會變為２倍。"
  },
  "past_values": [
    {
      "changed_in": 30,
      "prior_values": {
        "flavor_text_entries": {
          "ja": "物理攻撃の 威力が　あがる。",
          "kana": "ぶつり　こうげきの いりょくが　あがる。",
          "en": "Boosts the Pokémon’s Attack stat.",
          "fr": "Augmente l’Attaque du Pokémon.",
          "it": "Migliora la statistica Attacco del Pokémon.",
          "de": "Stärkt physische Attacken.",
          "es": "Aumenta el Ataque.",
          "ko": "물리공격의 위력이 올라간다."
        }
      }
    }
  ]
}
