{
  "id": 97,
  "name": "sniper",
  "names": {
    "ja": "スナイパー",
    "kana": "スナイパー",
    "en": "Sniper",
    "fr": "Sniper",
    "it": "Cecchino",
    "de": "Superschütze",
    "es": "Francotirador",
    "ko": "스나이퍼",
    "zh-CN": "狙击手",
    "zh-TW": "狙擊手"
  },
  "flavor_text_entries": {
    "ja": "攻撃を　急所に　当てると 威力が　さらに　上がる。",
    "kana": "こうげきを　きゅうしょに　あてると いりょくが　さらに　あがる。",
    "en": "Powers up moves if they become critical hits when attacking.",
    "fr": "Lorsque le Pokémon porte un coup critique, les dégâts infligés augmentent encore plus que d’habitude.",
    "it": "Aumenta ulteriormente i danni inflitti dai brutti colpi.",
    "de": "Erhöht bei Volltreffern die Stärke der Attacke noch weiter.",
    "es": "Potencia los golpes críticos aún más de lo normal.",
    "ko": "공격을 급소에 맞혔을 때 위력이 더욱 올라간다.",
    "zh-CN": "击中要害时， 威力会变得更强。",
    "zh-TW": "擊中要害時， 威力會進一步提高。"
  },
  "past_values": [
    {
      "changed_in": 30,
      "prior_values": {
        "flavor_text_entries": {
          "ja": "急所に　当てたとき 威力が　あがる。",
          "kana": "きゅうしょに　あてたとき いりょくが　あがる。",
          "en": "Powers up moves if they become critical hits.",
          "fr": "Augmente la puissance des coups critiques.",
          "it": "Aumenta i danni inflitti dai brutti colpi.",
          "de": "Steigert den Schaden von Volltreffern.",
          "es": "Potencia los movimientos si se vuelven críticos.",
          "ko": "급소에 맞혔을 때 위력이 올라간다."
        }
      }
    }
  ]
}
