{"id":377,"name":"heal-block","accuracy":100,"effect_chance":null,"pp":15,"priority":0,"power":null,"contest_combos":null,"contest_type":{"name":"cute"},"contest_effect":null,"damage_class":{"name":"status"},"effect_entries":[{"effect":"For the next five turns, the target may not use any moves that only restore [HP]{mechanic:hp}, and move effects that heal the target are disabled.  Moves that steal [HP]{mechanic:hp} may still be used, but will only inflict damage and not heal the target.","short_effect":"Prevents target from restoring its HP for five turns.","language":"en"}],"effect_changes":[],"generation":{"name":"generation-iv"},"meta":{"ailment":{"name":"heal-block"},"category":{"name":"ailment"},"min_hits":null,"max_hits":null,"min_turns":5,"max_turns":5,"drain":0,"healing":0,"crit_rate":0,"ailment_chance":0,"flinch_chance":0,"stat_chance":0},"names":[{"name":"Heal Block","language":"en"},{"name":"Anticura","language":"it"},{"name":"Anticura","language":"es"},{"name":"Heilblockade","language":"de"},{"name":"Anti-Soin","language":"fr"},{"name":"회복봉인","language":"ko"},{"name":"かいふくふうじ","language":"ja"}],"past_values":[],"stat_changes":[],"super_contest_effect":{},"target":{"name":"all-opponents"},"type":{"name":"psychic"}}