{"id":38,"name":"poison-point","is_main_series":true,"generation":{"name":"generation-iii"},"names":[{"name":"Poison Point","language":"en"},{"name":"Velenopunto","language":"it"},{"name":"Punto Tóxico","language":"es"},{"name":"Giftdorn","language":"de"},{"name":"Point Poison","language":"fr"},{"name":"독가시","language":"ko"},{"name":"どくのトゲ","language":"ja"}],"effect_entries":[{"effect":"Whenever a move makes contact with this Pokémon, the move's user has a 30% chance of being [poisoned]{mechanic:poison}.","short_effect":"Has a 30% chance of [poisoning]{mechanic:poison} attacking Pokémon on contact.","language":"en"}],"effect_changes":[],"flavor_text_entries":[{"flavor_text":"触れた　相手に　どくを\nおわせる　ことがある。","version_group":{"name":"x-y"},"language":"ja-kanji"},{"flavor_text":"Contact with the Pokémon\nmay poison the attacker.","version_group":{"name":"x-y"},"language":"en"},{"flavor_text":"Può avvelenare chi manda\na segno una mossa fisica.","version_group":{"name":"x-y"},"language":"it"},{"flavor_text":"Puede envenenar al mínimo\ncontacto.","version_group":{"name":"x-y"},"language":"es"},{"flavor_text":"Vergiftet den Angreifer\neventuell bei Berührung.","version_group":{"name":"x-y"},"language":"de"},{"flavor_text":"Peut empoisonner l’attaquant\ns’il y a contact.","version_group":{"name":"x-y"},"language":"fr"},{"flavor_text":"접촉한 상대를\n중독시킬 때가 있다.","version_group":{"name":"x-y"},"language":"ko"},{"flavor_text":"ふれた　あいてに　どくを\nおわせる　ことがある。","version_group":{"name":"x-y"},"language":"ja"},{"flavor_text":"Contact with the Pokémon\nmay poison the attacker.","version_group":{"name":"black-2-white-2"},"language":"en"},{"flavor_text":"Contact with the Pokémon\nmay poison the attacker.","version_group":{"name":"black-white"},"language":"en"},{"flavor_text":"Peut empoisonner l’ennemi\ns’il y a contact.","version_group":{"name":"black-white"},"language":"fr"},{"flavor_text":"Contact with the Pokémon\nmay poison the foe.","version_group":{"name":"heartgold-soulsilver"},"language":"en"},{"flavor_text":"Contact with the Pokémon\nmay poison the foe.","version_group":{"name":"platinum"},"language":"en"},{"flavor_text":"Contact with the Pokémon\nmay poison the foe.","version_group":{"name":"diamond-pearl"},"language":"en"},{"flavor_text":"Poisons foe on contact.","version_group":{"name":"firered-leafgreen"},"language":"en"},{"flavor_text":"Poisons foe on contact.","version_group":{"name":"emerald"},"language":"en"},{"flavor_text":"Poisons foe on contact.","version_group":{"name":"ruby-sapphire"},"language":"en"}],"pokemon":[{"is_hidden":false,"slot":1,"pokemon":{"name":"nidoran-f"}},{"is_hidden":false,"slot":1,"pokemon":{"name":"nidorina"}},{"is_hidden":false,"slot":1,"pokemon":{"name":"nidoqueen"}},{"is_hidden":false,"slot":1,"pokemon":{"name":"nidoran-m"}},{"is_hidden":false,"slot":1,"pokemon":{"name":"nidorino"}},{"is_hidden":false,"slot":1,"pokemon":{"name":"nidoking"}},{"is_hidden":false,"slot":1,"pokemon":{"name":"seadra"}},{"is_hidden":false,"slot":1,"pokemon":{"name":"qwilfish"}},{"is_hidden":false,"slot":2,"pokemon":{"name":"roselia"}},{"is_hidden":false,"slot":2,"pokemon":{"name":"budew"}},{"is_hidden":false,"slot":2,"pokemon":{"name":"roserade"}},{"is_hidden":false,"slot":1,"pokemon":{"name":"venipede"}},{"is_hidden":false,"slot":1,"pokemon":{"name":"whirlipede"}},{"is_hidden":false,"slot":1,"pokemon":{"name":"scolipede"}},{"is_hidden":false,"slot":1,"pokemon":{"name":"skrelp"}},{"is_hidden":false,"slot":1,"pokemon":{"name":"dragalge"}}]}