{
  "id": 214,
  "name": "soft-sand",
  "cost": 100,
  "fling_power": 10,
  "fling_effect": null,
  "attributes": [
    {
      "name": "holdable"
    },
    {
      "name": "holdable-active"
    }
  ],
  "category": {
    "name": "type-enhancement"
  },
  "effect_entries": [
    {
      "effect": "Held: Increases the power of the holder's Ground moves by 20%.",
      "short_effect": "Held: Ground-Type moves from holder do 20% more damage.",
      "language": "en"
    }
  ],
  "flavor_text_entries": [
    {
      "text": "さわると　サラサラする　砂。\n持たせると　じめんタイプの\n技の　威力が　あがる。",
      "version_group": {
        "name": "x-y"
      },
      "language": "ja-kanji"
    },
    {
      "text": "An item to be held by a Pokémon.\nIt is a loose, silky sand that boosts\nthe power of Ground-type moves.",
      "version_group": {
        "name": "x-y"
      },
      "language": "en"
    },
    {
      "text": "Strumento da dare a un Pokémon.\nSabbia leggera e farinosa che potenzia le mosse\ndi tipo Terra.",
      "version_group": {
        "name": "x-y"
      },
      "language": "it"
    },
    {
      "text": "Tiene un curioso aroma que potencia los\nmovimientos de tipo Agua. Debe llevarlo un\nPokémon.",
      "version_group": {
        "name": "x-y"
      },
      "language": "es"
    },
    {
      "text": "Ein Item zum Tragen. Samtiger Sand,\nder Attacken vom Typ Boden verstärkt.",
      "version_group": {
        "name": "x-y"
      },
      "language": "de"
    },
    {
      "text": "Objet à tenir. Du sable fin et soyeux qui\naugmente la puissance des capacités de\ntype Sol.",
      "version_group": {
        "name": "x-y"
      },
      "language": "fr"
    },
    {
      "text": "만지면 보슬보슬한 모래.\n지니게 하면 땅타입\n기술의 위력이 올라간다.",
      "version_group": {
        "name": "x-y"
      },
      "language": "ko"
    },
    {
      "text": "さわると　サラサラする　すな。\nもたせると　じめんタイプの\nわざの　いりょくが　あがる。",
      "version_group": {
        "name": "x-y"
      },
      "language": "ja"
    },
    {
      "text": "An item to be held by a Pokémon.\nIt is a loose, silky sand that boosts\nthe power of Ground-type moves.",
      "version_group": {
        "name": "black-2-white-2"
      },
      "language": "en"
    },
    {
      "text": "An item to be held by a Pokémon.\nIt is a loose, silky sand that boosts\nthe power of Ground-type moves.",
      "version_group": {
        "name": "black-white"
      },
      "language": "en"
    },
    {
      "text": "Objet à tenir. Sable fin et soyeux\nmontant la puissance des capacités\nde type Sol.",
      "version_group": {
        "name": "black-white"
      },
      "language": "fr"
    },
    {
      "text": "An item to be held by a Pokémon.\nIt is a loose, silky sand that boosts\nthe power of Ground-type moves.",
      "version_group": {
        "name": "heartgold-soulsilver"
      },
      "language": "en"
    },
    {
      "text": "An item to be held by a Pokémon.\nIt is a loose, silky sand that boosts\nthe power of Ground-type moves.",
      "version_group": {
        "name": "platinum"
      },
      "language": "en"
    },
    {
      "text": "An item to be held by a Pokémon.\nIt is a loose, silky sand that boosts\nthe power of Ground-type moves.",
      "version_group": {
        "name": "diamond-pearl"
      },
      "language": "en"
    },
    {
      "text": "An item to be held by a POKéMON.\nA loose, silky sand that boosts the\npower of GROUND-type moves.",
      "version_group": {
        "name": "firered-leafgreen"
      },
      "language": "en"
    },
    {
      "text": "A hold item that\nraises the power of\nGROUND-type moves.",
      "version_group": {
        "name": "emerald"
      },
      "language": "en"
    },
    {
      "text": "A hold item that\nraises the power of\nGROUND-type moves.",
      "version_group": {
        "name": "ruby-sapphire"
      },
      "language": "en"
    }
  ],
  "game_indices": [
    {
      "game_index": 237,
      "generation": {
        "name": "generation-vi"
      }
    },
    {
      "game_index": 237,
      "generation": {
        "name": "generation-v"
      }
    },
    {
      "game_index": 237,
      "generation": {
        "name": "generation-iv"
      }
    },
    {
      "game_index": 203,
      "generation": {
        "name": "generation-iii"
      }
    }
  ],
  "names": [
    {
      "name": "Soft Sand",
      "language": "en"
    },
    {
      "name": "Sabbia Soffice",
      "language": "it"
    },
    {
      "name": "Arena Fina",
      "language": "es"
    },
    {
      "name": "Pudersand",
      "language": "de"
    },
    {
      "name": "Sable Doux",
      "language": "fr"
    },
    {
      "name": "부드러운모래",
      "language": "ko"
    },
    {
      "name": "やわらかいすな",
      "language": "ja"
    }
  ],
  "held_by_pokemon": [
    {
      "pokemon": {
        "name": "sandslash"
      },
      "version_details": [
        {
          "rarity": 5,
          "version": {
            "name": "leafgreen"
          }
        },
        {
          "rarity": 5,
          "version": {
            "name": "firered"
          }
        }
      ]
    },
    {
      "pokemon": {
        "name": "diglett"
      },
      "version_details": [
        {
          "rarity": 5,
          "version": {
            "name": "y"
          }
        },
        {
          "rarity": 5,
          "version": {
            "name": "x"
          }
        },
        {
          "rarity": 5,
          "version": {
            "name": "white-2"
          }
        },
        {
          "rarity": 5,
          "version": {
            "name": "black-2"
          }
        },
        {
          "rarity": 5,
          "version": {
            "name": "white"
          }
        },
        {
          "rarity": 5,
          "version": {
            "name": "black"
          }
        },
        {
          "rarity": 5,
          "version": {
            "name": "soulsilver"
          }
        },
        {
          "rarity": 5,
          "version": {
            "name": "heartgold"
          }
        },
        {
          "rarity": 5,
          "version": {
            "name": "platinum"
          }
        },
        {
          "rarity": 5,
          "version": {
            "name": "pearl"
          }
        },
        {
          "rarity": 5,
          "version": {
            "name": "diamond"
          }
        }
      ]
    },
    {
      "pokemon": {
        "name": "dugtrio"
      },
      "version_details": [
        {
          "rarity": 5,
          "version": {
            "name": "y"
          }
        },
        {
          "rarity": 5,
          "version": {
            "name": "x"
          }
        },
        {
          "rarity": 5,
          "version": {
            "name": "white-2"
          }
        },
        {
          "rarity": 5,
          "version": {
            "name": "black-2"
          }
        },
        {
          "rarity": 5,
          "version": {
            "name": "white"
          }
        },
        {
          "rarity": 5,
          "version": {
            "name": "black"
          }
        },
        {
          "rarity": 5,
          "version": {
            "name": "soulsilver"
          }
        },
        {
          "rarity": 5,
          "version": {
            "name": "heartgold"
          }
        },
        {
          "rarity": 5,
          "version": {
            "name": "platinum"
          }
        },
        {
          "rarity": 5,
          "version": {
            "name": "pearl"
          }
        },
        {
          "rarity": 5,
          "version": {
            "name": "diamond"
          }
        }
      ]
    },
    {
      "pokemon": {
        "name": "trapinch"
      },
      "version_details": [
        {
          "rarity": 5,
          "version": {
            "name": "y"
          }
        },
        {
          "rarity": 5,
          "version": {
            "name": "x"
          }
        },
        {
          "rarity": 5,
          "version": {
            "name": "white-2"
          }
        },
        {
          "rarity": 5,
          "version": {
            "name": "black-2"
          }
        },
        {
          "rarity": 5,
          "version": {
            "name": "white"
          }
        },
        {
          "rarity": 5,
          "version": {
            "name": "black"
          }
        },
        {
          "rarity": 5,
          "version": {
            "name": "soulsilver"
          }
        },
        {
          "rarity": 5,
          "version": {
            "name": "heartgold"
          }
        },
        {
          "rarity": 5,
          "version": {
            "name": "platinum"
          }
        },
        {
          "rarity": 5,
          "version": {
            "name": "pearl"
          }
        },
        {
          "rarity": 5,
          "version": {
            "name": "diamond"
          }
        },
        {
          "rarity": 5,
          "version": {
            "name": "leafgreen"
          }
        },
        {
          "rarity": 5,
          "version": {
            "name": "firered"
          }
        },
        {
          "rarity": 5,
          "version": {
            "name": "emerald"
          }
        },
        {
          "rarity": 5,
          "version": {
            "name": "sapphire"
          }
        },
        {
          "rarity": 5,
          "version": {
            "name": "ruby"
          }
        }
      ]
    },
    {
      "pokemon": {
        "name": "stunfisk"
      },
      "version_details": [
        {
          "rarity": 5,
          "version": {
            "name": "y"
          }
        },
        {
          "rarity": 5,
          "version": {
            "name": "x"
          }
        },
        {
          "rarity": 5,
          "version": {
            "name": "white-2"
          }
        },
        {
          "rarity": 5,
          "version": {
            "name": "black-2"
          }
        },
        {
          "rarity": 5,
          "version": {
            "name": "white"
          }
        },
        {
          "rarity": 5,
          "version": {
            "name": "black"
          }
        }
      ]
    }
  ],
  "baby_trigger_for": null
}