{
  "id": 284,
  "name": "mind-plate",
  "cost": 1000,
  "fling_power": 90,
  "fling_effect": null,
  "attributes": [
    {
      "name": "holdable"
    },
    {
      "name": "holdable-active"
    },
    {
      "name": "underground"
    }
  ],
  "category": {
    "name": "plates"
  },
  "effect_entries": [
    {
      "effect": "Held: Increases the power of the holder's Psychic moves by 20%.\nHeld by a Multitype Pokémon: Holder's type becomes Psychic.",
      "short_effect": "Held: Psychic-Type moves from holder do 20% more damage. Changes Arceus's and Judgment's type to Psychic.",
      "language": "en"
    }
  ],
  "flavor_text_entries": [
    {
      "text": "エスパーの　タイプの　石盤。\n持たせると　エスパータイプの\n技の　威力が　強まる。",
      "version_group": {
        "name": "x-y"
      },
      "language": "ja-kanji"
    },
    {
      "text": "An item to be held by a Pokémon.\nIt’s a stone tablet that boosts the\npower of Psychic-type moves.",
      "version_group": {
        "name": "x-y"
      },
      "language": "en"
    },
    {
      "text": "Strumento da dare a un Pokémon.\nLastra di pietra che potenzia le mosse\ndi tipo Psico.",
      "version_group": {
        "name": "x-y"
      },
      "language": "it"
    },
    {
      "text": "Dispositivo transparente que contiene datos\nmisteriosos. Es de fabricante desconocido.",
      "version_group": {
        "name": "x-y"
      },
      "language": "es"
    },
    {
      "text": "Ein Item zum Tragen. Diese Steintafel verstärkt\nAttacken vom Typ Psycho.",
      "version_group": {
        "name": "x-y"
      },
      "language": "de"
    },
    {
      "text": "Objet à tenir. Une tablette en pierre augmentant\nla puissance des capacités de type Psy.",
      "version_group": {
        "name": "x-y"
      },
      "language": "fr"
    },
    {
      "text": "에스퍼타입의 석판.\n지니게 하면 에스퍼타입\n기술의 위력이 강해진다.",
      "version_group": {
        "name": "x-y"
      },
      "language": "ko"
    },
    {
      "text": "エスパーの　タイプの　せきばん。\nもたせると　エスパータイプの\nわざの　いりょくが　つよまる。",
      "version_group": {
        "name": "x-y"
      },
      "language": "ja"
    },
    {
      "text": "An item to be held by a Pokémon.\nIt is a stone tablet that boosts the\npower of Psychic-type moves.",
      "version_group": {
        "name": "black-2-white-2"
      },
      "language": "en"
    },
    {
      "text": "An item to be held by a Pokémon.\nIt is a stone tablet that boosts the\npower of Psychic-type moves.",
      "version_group": {
        "name": "black-white"
      },
      "language": "en"
    },
    {
      "text": "Objet à tenir. Tablette en pierre\naugmentant la puissance des capacités\nde type Psy.",
      "version_group": {
        "name": "black-white"
      },
      "language": "fr"
    },
    {
      "text": "An item to be held by a Pokémon.\nIt is a stone tablet that boosts the\npower of Psychic-type moves.",
      "version_group": {
        "name": "heartgold-soulsilver"
      },
      "language": "en"
    },
    {
      "text": "An item to be held by a Pokémon.\nIt is a stone tablet that boosts the\npower of Psychic-type moves.",
      "version_group": {
        "name": "platinum"
      },
      "language": "en"
    },
    {
      "text": "An item to be held by a Pokémon.\nIt is a stone tablet that boosts the\npower of Psychic-type moves.",
      "version_group": {
        "name": "diamond-pearl"
      },
      "language": "en"
    }
  ],
  "game_indices": [
    {
      "game_index": 307,
      "generation": {
        "name": "generation-vi"
      }
    },
    {
      "game_index": 307,
      "generation": {
        "name": "generation-v"
      }
    },
    {
      "game_index": 307,
      "generation": {
        "name": "generation-iv"
      }
    }
  ],
  "names": [
    {
      "name": "Mind Plate",
      "language": "en"
    },
    {
      "name": "Lastramente",
      "language": "it"
    },
    {
      "name": "Tabla Mental",
      "language": "es"
    },
    {
      "name": "Hirntafel",
      "language": "de"
    },
    {
      "name": "Plaque Esprit",
      "language": "fr"
    },
    {
      "name": "이상한플레이트",
      "language": "ko"
    },
    {
      "name": "ふしぎのプレート",
      "language": "ja"
    }
  ],
  "held_by_pokemon": [],
  "baby_trigger_for": null
}