{"id":388,"name":"tm84","cost":3000,"fling_power":null,"fling_effect":null,"attributes":[],"category":{"name":"all-machines"},"effect_entries":[{"effect":"Teaches Poison Jab to a compatible Pokémon.","short_effect":"Teaches Poison Jab to a compatible Pokémon.","language":"en"}],"flavor_text_entries":[{"text":"毒に　そまった　触手や　腕で\n相手を　突き刺す。\n毒状態に　することが　ある。","version_group":{"name":"x-y"},"language":"ja-kanji"},{"text":"The target is stabbed with a tentacle\nor arm steeped in poison. This may also\npoison the target.","version_group":{"name":"x-y"},"language":"en"},{"text":"Il nemico è colpito da un tentacolo o da un arto\nintriso di una sostanza tossica che può anche\navvelenarlo.","version_group":{"name":"x-y"},"language":"it"},{"text":"Recoge las normas de los combates. En los\ncombates en conexión puedes elegir el conjunto\nde reglas que quieres usar.","version_group":{"name":"x-y"},"language":"es"},{"text":"Der Anwender greift mit giftigen Tentakeln oder\nArmen an. Das Ziel wird dabei eventuell vergiftet.","version_group":{"name":"x-y"},"language":"de"},{"text":"Attaque l’ennemi avec un tentacule ou un bras\nplein de poison. Peut aussi l’empoisonner.","version_group":{"name":"x-y"},"language":"fr"},{"text":"독에 물든 촉수나 팔로\n상대를 꿰찌른다.\n독 상태로 만들 때가 있다.","version_group":{"name":"x-y"},"language":"ko"},{"text":"どくに　そまった　しょくしゅや\nうでで　こうげきする。どくの\nじょうたいに　することが　ある。","version_group":{"name":"x-y"},"language":"ja"},{"text":"The target is stabbed with a tentacle\nor arm steeped in poison. It may also\npoison the target.","version_group":{"name":"black-2-white-2"},"language":"en"},{"text":"The target is stabbed with a tentacle\nor arm steeped in poison. It may also\npoison the target.","version_group":{"name":"black-white"},"language":"en"},{"text":"Attaque l’ennemi avec un tentacule ou\nun bras plein de poison. Peut aussi\nl’empoisonner.","version_group":{"name":"black-white"},"language":"fr"},{"text":"The foe is stabbed with a tentacle or\narm steeped with poison. It may also\npoison the foe.","version_group":{"name":"heartgold-soulsilver"},"language":"en"},{"text":"The foe is stabbed with a tentacle or\narm seeped with poison. It may also\npoison the foe.","version_group":{"name":"platinum"},"language":"en"},{"text":"The foe is stabbed with a tentacle or\narm seeped with poison. It may also\npoison the foe.","version_group":{"name":"diamond-pearl"},"language":"en"}],"game_indices":[{"game_index":411,"generation":{"name":"generation-vi"}},{"game_index":411,"generation":{"name":"generation-v"}},{"game_index":411,"generation":{"name":"generation-iv"}}],"names":[{"name":"TM84","language":"en"},{"name":"MT84","language":"it"},{"name":"MT84","language":"es"},{"name":"TM84","language":"de"},{"name":"CT84","language":"fr"},{"name":"기술머신84","language":"ko"},{"name":"わざマシン８４","language":"ja"}],"held_by_pokemon":[],"baby_trigger_for":null}