{
  "id": 710,
  "name": "pinsirite",
  "cost": 0,
  "fling_power": null,
  "fling_effect": null,
  "attributes": [],
  "category": {
    "name": "mega-stones"
  },
  "effect_entries": [],
  "flavor_text_entries": [
    {
      "text": "カイロスに　持たせておくと\n戦いのとき　メガシンカが　できる\n不思議な　メガストーンの　一種。",
      "version_group": {
        "name": "x-y"
      },
      "language": "ja-kanji"
    },
    {
      "text": "One variety of the mysterious Mega Stones.\nHave Pinsir hold it, and this stone will\nenable it to Mega Evolve during battle.",
      "version_group": {
        "name": "x-y"
      },
      "language": "en"
    },
    {
      "text": "Un esemplare delle misteriose Megapietre.\nData a Pinsir, gli permette di megaevolversi\ndurante la lotta.",
      "version_group": {
        "name": "x-y"
      },
      "language": "it"
    },
    {
      "text": "Usa el poder de la naturaleza para atacar.\nSu efecto varía según el entorno de combate.",
      "version_group": {
        "name": "x-y"
      },
      "language": "es"
    },
    {
      "text": "Einer der mysteriösen Mega-Steine. Wird er von\neinem Pinsir getragen, kann es im Kampf eine\nMega-Entwicklung durchführen.",
      "version_group": {
        "name": "x-y"
      },
      "language": "de"
    },
    {
      "text": "Une variété de Méga-Gemme.\nTenue par un Scarabrute, elle lui permet de\nméga-évoluer durant un combat.",
      "version_group": {
        "name": "x-y"
      },
      "language": "fr"
    },
    {
      "text": "쁘사이저에게 지니게 하면\n배틀할 때 메가진화할 수 있는\n신비한 메가스톤의 일종.",
      "version_group": {
        "name": "x-y"
      },
      "language": "ko"
    },
    {
      "text": "カイロスに　もたせておくと\nたたかいのとき　メガシンカが　できる\nふしぎな　メガストーンの　いっしゅ。",
      "version_group": {
        "name": "x-y"
      },
      "language": "ja"
    }
  ],
  "game_indices": [
    {
      "game_index": 671,
      "generation": {
        "name": "generation-vi"
      }
    }
  ],
  "names": [
    {
      "name": "Pinsirite",
      "language": "en"
    },
    {
      "name": "Pinsirite",
      "language": "it"
    },
    {
      "name": "Pinsirita",
      "language": "es"
    },
    {
      "name": "Pinsirnit",
      "language": "de"
    },
    {
      "name": "Scarabruite",
      "language": "fr"
    },
    {
      "name": "쁘사이저나이트",
      "language": "ko"
    },
    {
      "name": "カイロスナイト",
      "language": "ja"
    }
  ],
  "held_by_pokemon": [],
  "baby_trigger_for": null
}