{"id":737,"name":"lens-case","cost":0,"fling_power":null,"fling_effect":null,"attributes":[],"category":{"name":"gameplay"},"effect_entries":[],"flavor_text_entries":[{"text":"コンタクトレンズを　しまっておける\nちょっと　おしゃれな　ケース。\n","version_group":{"name":"x-y"},"language":"ja-kanji"},{"text":"A rather chic-looking case\nfor carrying contact lenses.","version_group":{"name":"x-y"},"language":"en"},{"text":"Un’elegante custodia per lenti a contatto.","version_group":{"name":"x-y"},"language":"it"},{"text":"","version_group":{"name":"x-y"},"language":"es"},{"text":"Ein sehr stilvolles Etui zur Aufbewahrung\nvon Kontaktlinsen.","version_group":{"name":"x-y"},"language":"de"},{"text":"Un étui plutôt chic destiné aux lentilles de\ncontact.","version_group":{"name":"x-y"},"language":"fr"},{"text":"콘택트렌즈를 담아둘 수 있는\n살짝 멋진 케이스.","version_group":{"name":"x-y"},"language":"ko"},{"text":"コンタクトレンズを　しまっておける\nちょっと　おしゃれな　ケース。\n","version_group":{"name":"x-y"},"language":"ja"}],"game_indices":[{"game_index":705,"generation":{"name":"generation-vi"}}],"names":[{"name":"Lens Case","language":"en"},{"name":"Portalenti","language":"it"},{"name":"Portalentillas","language":"es"},{"name":"Linsenetui","language":"de"},{"name":"Boîte Lentilles","language":"fr"},{"name":"렌즈케이스","language":"ko"},{"name":"レンズケース","language":"ja"}],"held_by_pokemon":[],"baby_trigger_for":null}